{"children":[{"fileID":"8782078619488769060","name":"Mug_005","tag":"Pot","active":1,"components":[{"fileID":"8782078619488471044","type":"transform","position":{"x":3.42,"y":0,"z":0},"rotation":{"x":0,"y":0,"z":0,"w":1},"scale":{"x":2,"y":2,"z":2},"parent":"0"},{"fileID":"8782078619487668260","type":"mesh","meshScale":1,"mesh":"assets/models/kitchen/mug-005","meshName":"Mug_005"},{"fileID":"8782078619486571236","type":"renderer","enabled":1,"castShadow":1,"receiveShadow":1,"materials":[{"name":"AllColors","color":{"r":1,"g":1,"b":1},"emissive":{"r":0,"g":0,"b":0},"texture":"assets/materials/allcolors"}]},{"fileID":"8395450402801596145","type":"boxCollider","size":{"x":0.22654605,"y":0.2044773,"z":0.19652748},"center":{"x":-3.7252903e-9,"y":0.10223865,"z":7.450581e-9},"isTrigger":0},{"fileID":"4907258424436239312","type":"rigidbody","mass":3,"useGravity":1,"kinematic":0}],"children":[]}]}