{"children":[{"fileID":"1457867963864516","name":"Bike","tag":"Untagged","active":1,"components":[{"fileID":"4016597444558024","type":"transform","position":{"x":12.17,"y":0,"z":-0.056},"rotation":{"x":0,"y":0,"z":0,"w":1},"scale":{"x":1,"y":1,"z":1},"parent":"0"},{"fileID":"33744970197541148","type":"mesh","meshScale":0.9999979999999999,"mesh":"assets/models/kidroom/bike","meshName":"Bike"},{"fileID":"23076109774970090","type":"renderer","enabled":1,"castShadow":1,"receiveShadow":1,"materials":[{"name":"AllColors","color":{"r":1,"g":1,"b":1},"emissive":{"r":0,"g":0,"b":0},"texture":"assets/materials/allcolors"}]},{"fileID":"65671873514949658","type":"boxCollider","size":{"x":1.673625,"y":0.3865528,"z":0.90576094},"center":{"x":-0.021520138,"y":0.81866455,"z":0},"isTrigger":1},{"fileID":"65549329887590020","type":"boxCollider","size":{"x":0.4343872,"y":0.35227156,"z":0.90576094},"center":{"x":-0.21212769,"y":0.4450357,"z":0},"isTrigger":0},{"fileID":"65699950260650076","type":"boxCollider","size":{"x":0.19970703,"y":0.7174723,"z":0.90576094},"center":{"x":0.40771484,"y":0.6040064,"z":0},"isTrigger":0},{"fileID":"65437731113008632","type":"boxCollider","size":{"x":0.80688477,"y":0.5637295,"z":0.90576094},"center":{"x":0.42504883,"y":0.28186476,"z":0},"isTrigger":0},{"fileID":"65146471956849082","type":"boxCollider","size":{"x":0.45999146,"y":0.36422467,"z":0.90576094},"center":{"x":-0.67655945,"y":0.18211234,"z":0},"isTrigger":0},{"fileID":"114692042314423480","type":"script","resetPosition":1,"resetRotation":1,"resetRigidbody":1,"thisRigidbody":{"fileID":"54011972511373318"},"script":"LevelObjSetter"},{"fileID":"54011972511373318","type":"rigidbody","mass":1,"useGravity":0,"kinematic":1},{"fileID":"114138132011845750","type":"script","thisTransform":{"fileID":4016597444558024},"destination":{"fileID":0},"duration":2,"typeOfObj":2,"script":"SkateboardMover"}],"children":[{"fileID":"1199233593409680","name":"GameObject","tag":"Untagged","active":1,"components":[{"fileID":"4786678185279182","type":"transform","position":{"x":0.24,"y":0.585,"z":0},"rotation":{"x":0,"y":0,"z":-0.41469333,"w":0.9099612},"scale":{"x":1,"y":1,"z":1},"parent":"4016597444558024"},{"fileID":"65545052459103682","type":"boxCollider","size":{"x":0.13669583,"y":0.73962986,"z":1},"center":{"x":-0.014772452,"y":-0.13018507,"z":0},"isTrigger":0}],"children":[]}]}]}